dsprpc
